BriCA1-1.0.0.dev0.dist-info/METADATA
BriCA1-1.0.0.dev0.dist-info/RECORD
BriCA1-1.0.0.dev0.dist-info/WHEEL
BriCA1-1.0.0.dev0.dist-info/top_level.txt
brica1/__init__.py
brica1/__version__.py
brica1/component.py
brica1/connection.py
brica1/gym.py
brica1/module.py
brica1/port.py
brica1/ros.py
brica1/scheduler.py
brica1/supervisor.py
brica1/unit.py
brica1/utils.py
