Metadata-Version: 2.1
Name: BriCA1
Version: 1.0.0.dev0
Summary: Brain-inspired Computing Architecture Version 1
Home-page: https://github.com/wbap/BriCA1
Author: Kotone Itaya
Author-email: kotone@sfc.keio.ac.jp
License: MIT
Platform: UNKNOWN
Classifier: License :: OSI Approved :: MIT License
Classifier: Programming Language :: Python
Classifier: Programming Language :: Python :: 3
Classifier: Programming Language :: Python :: 3.6
Classifier: Programming Language :: Python :: Implementation :: CPython
Classifier: Programming Language :: Python :: Implementation :: PyPy
Requires-Python: >=2.7.0
